ait_openapi/__init__.py
ait_openapi/authorize.py
ait_openapi/config.py
ait_openapi/exception.py
ait_openapi/log.py
ait_openapi/openapi_contexvar.py
ait_openapi/schema.py
ait_openapi/middleware/__init__.py
ait_openapi/middleware/context_middleware.py
ait_openapi-0.0.1.16.dist-info/METADATA
ait_openapi-0.0.1.16.dist-info/WHEEL
ait_openapi-0.0.1.16.dist-info/top_level.txt
ait_openapi-0.0.1.16.dist-info/RECORD
