Metadata-Version: 2.1
Name: ait-openapi
Version: 0.0.1.16
Summary: client for openapi service.
Home-page: UNKNOWN
Author: fanqiangwei
Author-email: fanqiangwei002@ke.com
License: UNKNOWN
Platform: any
Classifier: Programming Language :: Python :: 3.5
Requires-Dist: httpx (<=0.26.0,>=0.10.0)
Requires-Dist: Werkzeug (==3.0.1)
